pysk8/__init__.py
pysk8/__version__.py
pysk8/constants.py
pysk8/core.py
pysk8/discovery.py
pysk8/extana.py
pysk8/imu.py
pysk8/util.py
pysk8-0.0.17.dist-info/LICENSE
pysk8-0.0.17.dist-info/METADATA
pysk8-0.0.17.dist-info/WHEEL
pysk8-0.0.17.dist-info/top_level.txt
pysk8-0.0.17.dist-info/RECORD
