Metadata-Version: 2.1
Name: pysk8
Version: 0.0.17
Summary: Python driver for SK8 BLE sensor pack
Home-page: https://github.com/andrewramsay/sk8-drivers/pysk8
Author: Andrew Ramsay
Author-email: andrew.ramsay@gmail.com
License: MIT
Classifier: Development Status :: 4 - Beta
Classifier: Intended Audience :: Developers
Classifier: License :: OSI Approved :: MIT License
Classifier: Programming Language :: Python
Classifier: Programming Language :: Python :: 3.7
Classifier: Programming Language :: Python :: 3.8
Classifier: Programming Language :: Python :: 3.9
Classifier: Programming Language :: Python :: 3.10
Classifier: Programming Language :: Python :: 3.11
Classifier: Programming Language :: Python :: Implementation :: CPython
Requires-Python: >=3.7.0
License-File: LICENSE
Requires-Dist: bgapi
Requires-Dist: pyserial
Requires-Dist: future
